.DS_Store
shellbot/__init__.py
shellbot/bot.py
shellbot/bus.py
shellbot/channel.py
shellbot/context.py
shellbot/engine.py
shellbot/events.py
shellbot/i18n.py
shellbot/listener.py
shellbot/observer.py
shellbot/server.py
shellbot/shell.py
shellbot/speaker.py
shellbot/commands/__init__.py
shellbot/commands/audit.py
shellbot/commands/base.py
shellbot/commands/close.py
shellbot/commands/default.py
shellbot/commands/echo.py
shellbot/commands/empty.py
shellbot/commands/help.py
shellbot/commands/input.py
shellbot/commands/noop.py
shellbot/commands/sleep.py
shellbot/commands/start.py
shellbot/commands/step.py
shellbot/commands/update.py
shellbot/commands/upload.py
shellbot/commands/version.py
shellbot/machines/__init__.py
shellbot/machines/base.py
shellbot/machines/input.py
shellbot/machines/menu.py
shellbot/machines/sequence.py
shellbot/machines/steps.py
shellbot/routes/__init__.py
shellbot/routes/base.py
shellbot/routes/notifier.py
shellbot/routes/text.py
shellbot/routes/wrapper.py
shellbot/spaces/__init__.py
shellbot/spaces/base.py
shellbot/spaces/ciscospark.py
shellbot/spaces/local.py
shellbot/stores/__init__.py
shellbot/stores/base.py
shellbot/stores/memory.py
shellbot/stores/sqlite.py
shellbot/updaters/__init__.py
shellbot/updaters/base.py
shellbot/updaters/elastic.py
shellbot/updaters/file.py
shellbot/updaters/queue.py
shellbot/updaters/space.py
shellbot-17.10.20.dist-info/DESCRIPTION.rst
shellbot-17.10.20.dist-info/METADATA
shellbot-17.10.20.dist-info/RECORD
shellbot-17.10.20.dist-info/WHEEL
shellbot-17.10.20.dist-info/metadata.json
shellbot-17.10.20.dist-info/top_level.txt
