Metadata-Version: 2.0
Name: shellbot
Version: 17.10.20
Summary: A bot that is also a responsive shell
Home-page: https://github.com/bernard357/shellbot
Author: Bernard Paques
Author-email: bernard.paques@gmail.com
License: Apache License (2.0)
Keywords: bot,shell
Platform: UNKNOWN
Classifier: Development Status :: 2 - Pre-Alpha
Classifier: Environment :: No Input/Output (Daemon)
Classifier: Framework :: Bottle
Classifier: Framework :: Paste
Classifier: Framework :: Sphinx
Classifier: Intended Audience :: Developers
Classifier: Intended Audience :: Information Technology
Classifier: Intended Audience :: System Administrators
Classifier: License :: OSI Approved :: Apache Software License
Classifier: Operating System :: OS Independent
Classifier: Programming Language :: Python
Classifier: Programming Language :: Python :: 2.7
Classifier: Programming Language :: Python :: 3.5
Classifier: Programming Language :: Python :: Implementation :: CPython
Classifier: Topic :: Communications
Classifier: Topic :: Communications :: Chat
Classifier: Topic :: Communications :: Conferencing
Classifier: Topic :: Communications :: Internet Phone
Classifier: Topic :: Communications :: Telephony
Classifier: Topic :: Internet :: WWW/HTTP :: WSGI
Classifier: Topic :: Software Development :: Libraries :: Python Modules
Classifier: Topic :: System :: Shells
Requires-Dist: PyYAML
Requires-Dist: bottle
Requires-Dist: ciscosparkapi
Requires-Dist: colorlog
Requires-Dist: elasticsearch
Requires-Dist: paste
Requires-Dist: pyzmq
